flashyfly/builder.py
flashyfly/cli.py
flashyfly/flasher.py
flashyfly/init.py
flashyfly/initer.py
flashyfly/installer.py
flashyfly/__init__.py
flashyfly-0.1.3.dist-info/DESCRIPTION.rst
flashyfly-0.1.3.dist-info/entry_points.txt
flashyfly-0.1.3.dist-info/METADATA
flashyfly-0.1.3.dist-info/metadata.json
flashyfly-0.1.3.dist-info/RECORD
flashyfly-0.1.3.dist-info/top_level.txt
flashyfly-0.1.3.dist-info/WHEEL
scripts/cli.py
scripts/__init__.py
