Metadata-Version: 2.0
Name: flashyfly
Version: 0.1.3
Summary: Flashyfly package to build and flash firmware in production environment
Home-page: https://github.com/Lwao/flashyfly
Author: Levy Gabriel
Author-email: levygsg@hotmail.com
License: UNKNOWN
Keywords: python,build,flash,firmware,hardware
Platform: UNKNOWN
Classifier: Development Status :: 2 - Pre-Alpha
Classifier: Intended Audience :: Education
Classifier: Programming Language :: Python :: 3
Classifier: Operating System :: Microsoft :: Windows
Classifier: Operating System :: POSIX :: Linux
Requires-Dist: platformio
Requires-Dist: typer
